specsmith_cli/__init__.py
specsmith_cli/api_client.py
specsmith_cli/chat.py
specsmith_cli/config.py
specsmith_cli/constants.py
specsmith_cli/main.py
specsmith_cli/utils.py
specsmith_cli-0.1.5.dist-info/LICENSE
specsmith_cli-0.1.5.dist-info/METADATA
specsmith_cli-0.1.5.dist-info/WHEEL
specsmith_cli-0.1.5.dist-info/entry_points.txt
specsmith_cli-0.1.5.dist-info/RECORD
