Metadata-Version: 2.3
Name: specsmith-cli
Version: 0.1.5
Summary: Official command line interface for SpecSmith - AI-powered code generation and documentation
License: MIT
Keywords: cli,ai,chat,code-generation,specsmith,assistant,automation
Author: SpecSmith Team
Author-email: team@specsmith.ai
Requires-Python: >=3.9,<4.0
Classifier: Development Status :: 4 - Beta
Classifier: Intended Audience :: Developers
Classifier: License :: OSI Approved :: MIT License
Classifier: Operating System :: OS Independent
Classifier: Programming Language :: Python :: 3
Classifier: Programming Language :: Python :: 3.9
Classifier: Programming Language :: Python :: 3.10
Classifier: Programming Language :: Python :: 3.11
Classifier: Programming Language :: Python :: 3.12
Classifier: Programming Language :: Python :: 3.13
Classifier: Topic :: Communications :: Chat
Classifier: Topic :: Software Development :: Code Generators
Classifier: Topic :: Software Development :: Documentation
Classifier: Topic :: Software Development :: Libraries :: Python Modules
Classifier: Topic :: Utilities
Requires-Dist: click (>=8.1.0,<9.0.0)
Requires-Dist: httpx (>=0.25.0,<0.26.0)
Requires-Dist: prompt-toolkit (>=3.0.0,<4.0.0)
Requires-Dist: pydantic (>=2.0.0,<3.0.0)
Requires-Dist: rich (>=13.0.0,<14.0.0)
Project-URL: Documentation, https://github.com/specsmith-ai/specsmith-cli#readme
Project-URL: Homepage, https://specsmith.ai
Project-URL: Repository, https://github.com/specsmith-ai/specsmith-cli
